[
 {
  "completed_by": "alaa@akwad.qa",
  "docstatus": 0,
  "doctype": "Workflow Action",
  "modified": "2021-08-31 12:15:09.568432",
  "name": "9fb85cec1e",
  "parent": null,
  "parentfield": null,
  "parenttype": null,
  "reference_doctype": "Employee Advance",
  "reference_name": "HR-EAD-2021-00001",
  "status": "Completed",
  "user": "alaa@akwad.qa",
  "workflow_state": "Waiting for LM"
 },
 {
  "completed_by": "alaa@akwad.qa",
  "docstatus": 0,
  "doctype": "Workflow Action",
  "modified": "2021-08-31 13:17:01.837264",
  "name": "7c5ec949b6",
  "parent": null,
  "parentfield": null,
  "parenttype": null,
  "reference_doctype": "Expense Claim",
  "reference_name": "HR-EXP-2021-00001",
  "status": "Completed",
  "user": "alaa@akwad.qa",
  "workflow_state": "Waiting for LM"
 },
 {
  "completed_by": "santosh@akwad.qa",
  "docstatus": 0,
  "doctype": "Workflow Action",
  "modified": "2021-09-01 00:06:27.890706",
  "name": "80ea6b442c",
  "parent": null,
  "parentfield": null,
  "parenttype": null,
  "reference_doctype": "Employee Advance",
  "reference_name": "HR-EAD-2021-00002",
  "status": "Completed",
  "user": "santosh@akwad.qa",
  "workflow_state": "Waiting for LM"
 },
 {
  "completed_by": "alaa@akwad.qa",
  "docstatus": 0,
  "doctype": "Workflow Action",
  "modified": "2021-09-01 01:47:36.534623",
  "name": "a239b6724d",
  "parent": null,
  "parentfield": null,
  "parenttype": null,
  "reference_doctype": "Expense Claim",
  "reference_name": "HR-EXP-2021-00002",
  "status": "Completed",
  "user": "alaa@akwad.qa",
  "workflow_state": "Waiting for LM"
 },
 {
  "completed_by": "alaa@akwad.qa",
  "docstatus": 0,
  "doctype": "Workflow Action",
  "modified": "2021-09-01 14:05:58.729521",
  "name": "c0ce2a187d",
  "parent": null,
  "parentfield": null,
  "parenttype": null,
  "reference_doctype": "Employee Advance",
  "reference_name": "HR-EAD-2021-00003",
  "status": "Completed",
  "user": "alaa@akwad.qa",
  "workflow_state": "Waiting for LM"
 },
 {
  "completed_by": "alaa@akwad.qa",
  "docstatus": 0,
  "doctype": "Workflow Action",
  "modified": "2021-09-01 19:25:32.373311",
  "name": "3978c01ece",
  "parent": null,
  "parentfield": null,
  "parenttype": null,
  "reference_doctype": "Expense Claim",
  "reference_name": "HR-EXP-2021-00003",
  "status": "Completed",
  "user": "alaa@akwad.qa",
  "workflow_state": "Waiting for LM"
 },
 {
  "completed_by": "alaa@akwad.qa",
  "docstatus": 0,
  "doctype": "Workflow Action",
  "modified": "2021-09-01 19:46:08.183867",
  "name": "77977dcf4c",
  "parent": null,
  "parentfield": null,
  "parenttype": null,
  "reference_doctype": "Expense Claim",
  "reference_name": "HR-EXP-2021-00004",
  "status": "Completed",
  "user": "alaa@akwad.qa",
  "workflow_state": "Waiting for LM"
 },
 {
  "completed_by": "alaa@akwad.qa",
  "docstatus": 0,
  "doctype": "Workflow Action",
  "modified": "2021-09-01 19:58:30.674907",
  "name": "6a76e26c2a",
  "parent": null,
  "parentfield": null,
  "parenttype": null,
  "reference_doctype": "Expense Claim",
  "reference_name": "HR-EXP-2021-00005",
  "status": "Completed",
  "user": "alaa@akwad.qa",
  "workflow_state": "Waiting for LM"
 },
 {
  "completed_by": "alaa@akwad.qa",
  "docstatus": 0,
  "doctype": "Workflow Action",
  "modified": "2021-09-01 20:00:05.231647",
  "name": "57d7c01c0c",
  "parent": null,
  "parentfield": null,
  "parenttype": null,
  "reference_doctype": "Expense Claim",
  "reference_name": "HR-EXP-2021-00006",
  "status": "Completed",
  "user": "alaa@akwad.qa",
  "workflow_state": "Waiting for LM"
 },
 {
  "completed_by": "alaa@akwad.qa",
  "docstatus": 0,
  "doctype": "Workflow Action",
  "modified": "2021-09-12 11:08:34.050192",
  "name": "86d4ce0fdd",
  "parent": null,
  "parentfield": null,
  "parenttype": null,
  "reference_doctype": "Expense Claim",
  "reference_name": "HR-EXP-2021-00007",
  "status": "Completed",
  "user": "alaa@akwad.qa",
  "workflow_state": "Waiting for LM"
 },
 {
  "completed_by": "alaa@akwad.qa",
  "docstatus": 0,
  "doctype": "Workflow Action",
  "modified": "2021-09-12 14:34:08.686061",
  "name": "1cd6901c48",
  "parent": null,
  "parentfield": null,
  "parenttype": null,
  "reference_doctype": "Expense Claim",
  "reference_name": "HR-EXP-2021-00008",
  "status": "Completed",
  "user": "alaa@akwad.qa",
  "workflow_state": "Waiting for LM"
 },
 {
  "completed_by": "alaa@akwad.qa",
  "docstatus": 0,
  "doctype": "Workflow Action",
  "modified": "2021-09-12 14:36:57.220154",
  "name": "dc1b74ec25",
  "parent": null,
  "parentfield": null,
  "parenttype": null,
  "reference_doctype": "Expense Claim",
  "reference_name": "HR-EXP-2021-00009",
  "status": "Completed",
  "user": "alaa@akwad.qa",
  "workflow_state": "Waiting for LM"
 },
 {
  "completed_by": "alaa@akwad.qa",
  "docstatus": 0,
  "doctype": "Workflow Action",
  "modified": "2021-09-13 15:26:49.191102",
  "name": "5a6d9ee12c",
  "parent": null,
  "parentfield": null,
  "parenttype": null,
  "reference_doctype": "Expense Claim",
  "reference_name": "HR-EXP-2021-00010",
  "status": "Completed",
  "user": "alaa@akwad.qa",
  "workflow_state": "Waiting for LM"
 },
 {
  "completed_by": "alaa@akwad.qa",
  "docstatus": 0,
  "doctype": "Workflow Action",
  "modified": "2021-09-14 23:51:51.035101",
  "name": "b2a97296d9",
  "parent": null,
  "parentfield": null,
  "parenttype": null,
  "reference_doctype": "Expense Claim",
  "reference_name": "HR-EXP-2021-00011",
  "status": "Completed",
  "user": "alaa@akwad.qa",
  "workflow_state": "Waiting for LM"
 },
 {
  "completed_by": "alaa@akwad.qa",
  "docstatus": 0,
  "doctype": "Workflow Action",
  "modified": "2021-09-15 14:26:52.080068",
  "name": "f046b664f8",
  "parent": null,
  "parentfield": null,
  "parenttype": null,
  "reference_doctype": "Expense Claim",
  "reference_name": "HR-EXP-2021-00012",
  "status": "Completed",
  "user": "alaa@akwad.qa",
  "workflow_state": "Waiting for LM"
 },
 {
  "completed_by": "alaa@akwad.qa",
  "docstatus": 0,
  "doctype": "Workflow Action",
  "modified": "2021-09-18 22:39:10.338222",
  "name": "cca64b82c1",
  "parent": null,
  "parentfield": null,
  "parenttype": null,
  "reference_doctype": "Expense Claim",
  "reference_name": "HR-EXP-2021-00013",
  "status": "Completed",
  "user": "alaa@akwad.qa",
  "workflow_state": "Waiting for LM"
 },
 {
  "completed_by": "alaa@akwad.qa",
  "docstatus": 0,
  "doctype": "Workflow Action",
  "modified": "2021-09-18 22:43:58.780212",
  "name": "f2743d955a",
  "parent": null,
  "parentfield": null,
  "parenttype": null,
  "reference_doctype": "Expense Claim",
  "reference_name": "HR-EXP-2021-00014",
  "status": "Completed",
  "user": "alaa@akwad.qa",
  "workflow_state": "Waiting for LM"
 },
 {
  "completed_by": "alaa@akwad.qa",
  "docstatus": 0,
  "doctype": "Workflow Action",
  "modified": "2021-09-25 16:55:29.095486",
  "name": "b356cc9e51",
  "parent": null,
  "parentfield": null,
  "parenttype": null,
  "reference_doctype": "Expense Claim",
  "reference_name": "HR-EXP-2021-00015",
  "status": "Completed",
  "user": "alaa@akwad.qa",
  "workflow_state": "Waiting for LM"
 },
 {
  "completed_by": "alaa@akwad.qa",
  "docstatus": 0,
  "doctype": "Workflow Action",
  "modified": "2021-09-26 11:34:26.428696",
  "name": "8a74162d8c",
  "parent": null,
  "parentfield": null,
  "parenttype": null,
  "reference_doctype": "Expense Claim",
  "reference_name": "HR-EXP-2021-00016",
  "status": "Completed",
  "user": "alaa@akwad.qa",
  "workflow_state": "Waiting for LM"
 },
 {
  "completed_by": "alaa@akwad.qa",
  "docstatus": 0,
  "doctype": "Workflow Action",
  "modified": "2021-09-26 16:26:41.951128",
  "name": "44cf0403a0",
  "parent": null,
  "parentfield": null,
  "parenttype": null,
  "reference_doctype": "Expense Claim",
  "reference_name": "HR-EXP-2021-00017",
  "status": "Completed",
  "user": "alaa@akwad.qa",
  "workflow_state": "Waiting for LM"
 },
 {
  "completed_by": "alaa@akwad.qa",
  "docstatus": 0,
  "doctype": "Workflow Action",
  "modified": "2021-09-30 11:04:59.006708",
  "name": "185b710b83",
  "parent": null,
  "parentfield": null,
  "parenttype": null,
  "reference_doctype": "Expense Claim",
  "reference_name": "HR-EXP-2021-00018",
  "status": "Completed",
  "user": "alaa@akwad.qa",
  "workflow_state": "Waiting for LM"
 },
 {
  "completed_by": "alaa@akwad.qa",
  "docstatus": 0,
  "doctype": "Workflow Action",
  "modified": "2021-10-02 23:09:15.928781",
  "name": "212e122178",
  "parent": null,
  "parentfield": null,
  "parenttype": null,
  "reference_doctype": "Expense Claim",
  "reference_name": "HR-EXP-2021-00019",
  "status": "Completed",
  "user": "alaa@akwad.qa",
  "workflow_state": "Waiting for LM"
 },
 {
  "completed_by": "alaa@akwad.qa",
  "docstatus": 0,
  "doctype": "Workflow Action",
  "modified": "2021-10-04 10:22:35.099317",
  "name": "b5a9f3ca46",
  "parent": null,
  "parentfield": null,
  "parenttype": null,
  "reference_doctype": "Expense Claim",
  "reference_name": "HR-EXP-2021-00020",
  "status": "Completed",
  "user": "alaa@akwad.qa",
  "workflow_state": "Waiting for LM"
 },
 {
  "completed_by": "alaa@akwad.qa",
  "docstatus": 0,
  "doctype": "Workflow Action",
  "modified": "2021-10-09 15:09:51.924030",
  "name": "c84d513fa8",
  "parent": null,
  "parentfield": null,
  "parenttype": null,
  "reference_doctype": "Employee Advance",
  "reference_name": "HR-EAD-2021-00005",
  "status": "Completed",
  "user": "alaa@akwad.qa",
  "workflow_state": "Waiting for LM"
 },
 {
  "completed_by": "alaa@akwad.qa",
  "docstatus": 0,
  "doctype": "Workflow Action",
  "modified": "2021-10-09 16:02:41.023512",
  "name": "e408c8fc2a",
  "parent": null,
  "parentfield": null,
  "parenttype": null,
  "reference_doctype": "Expense Claim",
  "reference_name": "HR-EXP-2021-00021",
  "status": "Completed",
  "user": "alaa@akwad.qa",
  "workflow_state": "Waiting for LM"
 },
 {
  "completed_by": "alaa@akwad.qa",
  "docstatus": 0,
  "doctype": "Workflow Action",
  "modified": "2021-10-18 15:13:21.669123",
  "name": "08a55f587f",
  "parent": null,
  "parentfield": null,
  "parenttype": null,
  "reference_doctype": "Expense Claim",
  "reference_name": "HR-EXP-2021-00022",
  "status": "Completed",
  "user": "alaa@akwad.qa",
  "workflow_state": "Waiting for LM"
 },
 {
  "completed_by": "alaa@akwad.qa",
  "docstatus": 0,
  "doctype": "Workflow Action",
  "modified": "2021-10-18 15:42:12.153692",
  "name": "dc762017a4",
  "parent": null,
  "parentfield": null,
  "parenttype": null,
  "reference_doctype": "Employee Advance",
  "reference_name": "HR-EAD-2021-00006",
  "status": "Completed",
  "user": "alaa@akwad.qa",
  "workflow_state": "Waiting for LM"
 },
 {
  "completed_by": "alaa@akwad.qa",
  "docstatus": 0,
  "doctype": "Workflow Action",
  "modified": "2021-10-18 15:45:58.869662",
  "name": "0d9d77467c",
  "parent": null,
  "parentfield": null,
  "parenttype": null,
  "reference_doctype": "Expense Claim",
  "reference_name": "HR-EXP-2021-00023",
  "status": "Completed",
  "user": "alaa@akwad.qa",
  "workflow_state": "Waiting for LM"
 },
 {
  "completed_by": "alaa@akwad.qa",
  "docstatus": 0,
  "doctype": "Workflow Action",
  "modified": "2021-10-28 10:09:13.306874",
  "name": "1beaaf0218",
  "parent": null,
  "parentfield": null,
  "parenttype": null,
  "reference_doctype": "Expense Claim",
  "reference_name": "HR-EXP-2021-00024",
  "status": "Completed",
  "user": "alaa@akwad.qa",
  "workflow_state": "Waiting for LM"
 },
 {
  "completed_by": "alaa@akwad.qa",
  "docstatus": 0,
  "doctype": "Workflow Action",
  "modified": "2021-10-31 16:27:35.099537",
  "name": "eb3fedc463",
  "parent": null,
  "parentfield": null,
  "parenttype": null,
  "reference_doctype": "Employee Advance",
  "reference_name": "HR-EAD-2021-00007",
  "status": "Completed",
  "user": "alaa@akwad.qa",
  "workflow_state": "Waiting for LM"
 },
 {
  "completed_by": "alaa@akwad.qa",
  "docstatus": 0,
  "doctype": "Workflow Action",
  "modified": "2021-11-01 20:40:44.696346",
  "name": "77b0898e86",
  "parent": null,
  "parentfield": null,
  "parenttype": null,
  "reference_doctype": "Expense Claim",
  "reference_name": "HR-EXP-2021-00025",
  "status": "Completed",
  "user": "alaa@akwad.qa",
  "workflow_state": "Waiting for LM"
 },
 {
  "completed_by": "alaa@akwad.qa",
  "docstatus": 0,
  "doctype": "Workflow Action",
  "modified": "2021-11-03 12:28:23.134679",
  "name": "d9e189202f",
  "parent": null,
  "parentfield": null,
  "parenttype": null,
  "reference_doctype": "Expense Claim",
  "reference_name": "HR-EXP-2021-00026",
  "status": "Completed",
  "user": "alaa@akwad.qa",
  "workflow_state": "Waiting for LM"
 },
 {
  "completed_by": "alaa@akwad.qa",
  "docstatus": 0,
  "doctype": "Workflow Action",
  "modified": "2021-11-07 13:55:50.956018",
  "name": "4964ba382b",
  "parent": null,
  "parentfield": null,
  "parenttype": null,
  "reference_doctype": "Expense Claim",
  "reference_name": "HR-EXP-2021-00027",
  "status": "Completed",
  "user": "alaa@akwad.qa",
  "workflow_state": "Waiting for LM"
 },
 {
  "completed_by": "alaa@akwad.qa",
  "docstatus": 0,
  "doctype": "Workflow Action",
  "modified": "2021-11-07 13:57:33.953613",
  "name": "ff57efa738",
  "parent": null,
  "parentfield": null,
  "parenttype": null,
  "reference_doctype": "Expense Claim",
  "reference_name": "HR-EXP-2021-00028",
  "status": "Completed",
  "user": "alaa@akwad.qa",
  "workflow_state": "Waiting for LM"
 },
 {
  "completed_by": "alaa@akwad.qa",
  "docstatus": 0,
  "doctype": "Workflow Action",
  "modified": "2021-11-07 19:53:07.165893",
  "name": "51531afed5",
  "parent": null,
  "parentfield": null,
  "parenttype": null,
  "reference_doctype": "Expense Claim",
  "reference_name": "HR-EXP-2021-00029",
  "status": "Completed",
  "user": "alaa@akwad.qa",
  "workflow_state": "Waiting for LM"
 },
 {
  "completed_by": "alaa@akwad.qa",
  "docstatus": 0,
  "doctype": "Workflow Action",
  "modified": "2021-11-07 19:54:58.926479",
  "name": "5409cfd4c3",
  "parent": null,
  "parentfield": null,
  "parenttype": null,
  "reference_doctype": "Expense Claim",
  "reference_name": "HR-EXP-2021-00030",
  "status": "Completed",
  "user": "alaa@akwad.qa",
  "workflow_state": "Waiting for LM"
 },
 {
  "completed_by": "alaa@akwad.qa",
  "docstatus": 0,
  "doctype": "Workflow Action",
  "modified": "2021-11-14 16:50:33.181817",
  "name": "5f3da5d2b9",
  "parent": null,
  "parentfield": null,
  "parenttype": null,
  "reference_doctype": "Expense Claim",
  "reference_name": "HR-EXP-2021-00034",
  "status": "Completed",
  "user": "alaa@akwad.qa",
  "workflow_state": "Waiting for LM"
 },
 {
  "completed_by": "alaa@akwad.qa",
  "docstatus": 0,
  "doctype": "Workflow Action",
  "modified": "2021-11-14 16:53:11.742907",
  "name": "b7be4532f3",
  "parent": null,
  "parentfield": null,
  "parenttype": null,
  "reference_doctype": "Expense Claim",
  "reference_name": "HR-EXP-2021-00035",
  "status": "Completed",
  "user": "alaa@akwad.qa",
  "workflow_state": "Waiting for LM"
 },
 {
  "completed_by": "alaa@akwad.qa",
  "docstatus": 0,
  "doctype": "Workflow Action",
  "modified": "2021-11-15 18:41:01.996548",
  "name": "b5d994479c",
  "parent": null,
  "parentfield": null,
  "parenttype": null,
  "reference_doctype": "Expense Claim",
  "reference_name": "HR-EXP-2021-00036",
  "status": "Completed",
  "user": "alaa@akwad.qa",
  "workflow_state": "Waiting for LM"
 },
 {
  "completed_by": null,
  "docstatus": 0,
  "doctype": "Workflow Action",
  "modified": "2021-11-16 17:56:57.018734",
  "name": "492132043a",
  "parent": null,
  "parentfield": null,
  "parenttype": null,
  "reference_doctype": "Expense Claim",
  "reference_name": "HR-EXP-2021-00037",
  "status": "Open",
  "user": "alaa@akwad.qa",
  "workflow_state": "Waiting for LM"
 },
 {
  "completed_by": null,
  "docstatus": 0,
  "doctype": "Workflow Action",
  "modified": "2021-11-16 17:56:57.100973",
  "name": "675ab034bb",
  "parent": null,
  "parentfield": null,
  "parenttype": null,
  "reference_doctype": "Expense Claim",
  "reference_name": "HR-EXP-2021-00037",
  "status": "Open",
  "user": "santosh@akwad.qa",
  "workflow_state": "Waiting for LM"
 },
 {
  "completed_by": "alaa@akwad.qa",
  "docstatus": 0,
  "doctype": "Workflow Action",
  "modified": "2021-11-20 14:43:48.337674",
  "name": "980f77984b",
  "parent": null,
  "parentfield": null,
  "parenttype": null,
  "reference_doctype": "Employee Advance",
  "reference_name": "ADV21001",
  "status": "Completed",
  "user": "alaa@akwad.qa",
  "workflow_state": "Waiting for LM"
 },
 {
  "completed_by": null,
  "docstatus": 0,
  "doctype": "Workflow Action",
  "modified": "2021-11-20 18:29:07.137376",
  "name": "2b1fbcd0d9",
  "parent": null,
  "parentfield": null,
  "parenttype": null,
  "reference_doctype": "Employee Advance",
  "reference_name": "ADV21002",
  "status": "Open",
  "user": "alaa@akwad.qa",
  "workflow_state": "Waiting for LM"
 },
 {
  "completed_by": null,
  "docstatus": 0,
  "doctype": "Workflow Action",
  "modified": "2021-11-20 18:29:07.195557",
  "name": "bb5faa0485",
  "parent": null,
  "parentfield": null,
  "parenttype": null,
  "reference_doctype": "Employee Advance",
  "reference_name": "ADV21002",
  "status": "Open",
  "user": "santosh@akwad.qa",
  "workflow_state": "Waiting for LM"
 },
 {
  "completed_by": null,
  "docstatus": 0,
  "doctype": "Workflow Action",
  "modified": "2021-11-22 10:03:15.676707",
  "name": "3dc10b5b04",
  "parent": null,
  "parentfield": null,
  "parenttype": null,
  "reference_doctype": "Expense Claim",
  "reference_name": "EXP210002",
  "status": "Open",
  "user": "alaa@akwad.qa",
  "workflow_state": "Waiting for LM"
 },
 {
  "completed_by": null,
  "docstatus": 0,
  "doctype": "Workflow Action",
  "modified": "2021-11-22 10:03:15.721749",
  "name": "087153828f",
  "parent": null,
  "parentfield": null,
  "parenttype": null,
  "reference_doctype": "Expense Claim",
  "reference_name": "EXP210002",
  "status": "Open",
  "user": "santosh@akwad.qa",
  "workflow_state": "Waiting for LM"
 },
 {
  "completed_by": null,
  "docstatus": 0,
  "doctype": "Workflow Action",
  "modified": "2021-11-22 10:10:06.668114",
  "name": "edfcfc6967",
  "parent": null,
  "parentfield": null,
  "parenttype": null,
  "reference_doctype": "Expense Claim",
  "reference_name": "EXP210003",
  "status": "Open",
  "user": "alaa@akwad.qa",
  "workflow_state": "Waiting for LM"
 },
 {
  "completed_by": null,
  "docstatus": 0,
  "doctype": "Workflow Action",
  "modified": "2021-11-28 16:04:15.622109",
  "name": "5148377333",
  "parent": null,
  "parentfield": null,
  "parenttype": null,
  "reference_doctype": "Expense Claim",
  "reference_name": "EXP210004",
  "status": "Open",
  "user": "alaa@akwad.qa",
  "workflow_state": "Waiting for LM"
 },
 {
  "completed_by": null,
  "docstatus": 0,
  "doctype": "Workflow Action",
  "modified": "2021-11-28 16:08:51.882953",
  "name": "6ca6229e71",
  "parent": null,
  "parentfield": null,
  "parenttype": null,
  "reference_doctype": "Expense Claim",
  "reference_name": "EXP210005",
  "status": "Open",
  "user": "alaa@akwad.qa",
  "workflow_state": "Waiting for LM"
 },
 {
  "completed_by": null,
  "docstatus": 0,
  "doctype": "Workflow Action",
  "modified": "2021-11-30 21:04:25.348378",
  "name": "ef84a85801",
  "parent": null,
  "parentfield": null,
  "parenttype": null,
  "reference_doctype": "Expense Claim",
  "reference_name": "EXP210006",
  "status": "Open",
  "user": "alaa@akwad.qa",
  "workflow_state": "Waiting for LM"
 }
]